Week2/library.v
module and2(
    output y,
    input a,
    input b
    
);
assign y = a&b;
endmodule

module or2(
    output y,
    input a,
    input b
    
);
assign y = a|b;
endmodule

module not1(
    output y,
    input a
   );
assign y = !a;
endmodule

Week2/main.v
module main(A,B,C,D,E);
output D,E;
input A,B,C;
wire w1;
and2 G1(w1,A,B);
not1 G2(E,C);
or2 G3(D,w1,E);
endmodule

Week2/tb1.v
module tb1;
    reg A, B, C;
    wire D, E; 
    main M1 (A, B, C, D, E); //M1 is the instance name and this line defines an instance
    initial begin //Beginning of a block of code
        A = 1'b0; // 1'b means 1 byte
        B = 1'b0;
        C = 1'b0;

        #20 A = 1'b0; //#20 is refresh time
        B = 1'b0;
        C = 1'b1;

        #20 A = 1'b0;
        B = 1'b1;
        C = 1'b0;

        #20 A = 1'b0;
        B = 1'b1;
        C = 1'b1;

        #20 A = 1'b1;
        B = 1'b0;
        C = 1'b0;

        #20 A = 1'b1;
        B = 1'b0;
        C = 1'b1;

        #20 A = 1'b1;
        B = 1'b1;
        C = 1'b0;

        #20 A = 1'b1;
        B = 1'b1;
        C = 1'b1;
    end
    initial begin
        $monitor($time, "A = %b, B = %b, C = %b, D = %b, E = %b", A, B, C, D, E); //display on the monitor
    end
    initial begin
        $dumpfile("Circuit1.vcd"); 
        $dumpvars(1, tb1);
    end
endmodule

Week2/Circuit1.vcd
$date
	Fri Aug 23 14:17:47 2024
$end
$version
	Icarus Verilog
$end
$timescale
	1s
$end
$scope module tb1 $end
$var wire 1 ! E $end
$var wire 1 " D $end
$var reg 1 # A $end
$var reg 1 $ B $end
$var reg 1 % C $end
$upscope $end
$enddefinitions $end
$comment Show the parameter values. $end
$dumpall
$end
#0
$dumpvars
0%
0$
0#
1"
1!
$end
#20
0"
0!
1%
#40
1"
1!
0%
1$
#60
0"
0!
1%
#80
1"
1!
0%
0$
1#
#100
0"
0!
1%
#120
1"
1!
0%
1$
#140
0!
1%
