Week2/Circuit2.v
module Circuit2(
    A, 
    B, 
    C, 
    D
);

    input A, B, C;
    output D;
    wire w1;
    and G1 (w1, B, C);
    or G2 (D, A, w1);
endmodule

Week2/Circuit2tb.v
module Circuit2tb;
    reg A, B, C;
    wire D;
    Circuit2 M1 (A, B, C, D);
    initial begin
        A = 1'b0;
        B = 1'b0;
        C = 1'b0;

        #20 A = 1'b0;
        B = 1'b0;
        C = 1'b1;

        #20 A = 1'b0;
        B = 1'b1;
        C = 1'b0;

        #20 A = 1'b0;
        B = 1'b1;
        C = 1'b1;

        #20 A = 1'b1;
        B = 1'b0;
        C = 1'b0;

        #20 A = 1'b1;
        B = 1'b0;
        C = 1'b1;

        #20 A = 1'b1;
        B = 1'b1;
        C = 1'b0;

        #20 A = 1'b1;
        B = 1'b1;
        C = 1'b1;
    end
    initial begin
        $monitor($time, "A = %b, B = %b, C = %b, D = %b", A, B, C, D);
    end
    initial begin
        $dumpfile("Circuit2.vcd");
        $dumpvars(0, Circuit2tb);
    end
endmodule

Week2/s2.vcd
$date
	Fri Aug 16 15:47:13 2024
$end
$version
	Icarus Verilog
$end
$timescale
	1s
$end
$scope module Circuit2tb $end
$var wire 1 ! D $end
$var reg 1 " A $end
$var reg 1 # B $end
$var reg 1 $ C $end
$scope module M1 $end
$var wire 1 " A $end
$var wire 1 # B $end
$var wire 1 $ C $end
$var wire 1 ! D $end
$var wire 1 % w1 $end
$upscope $end
$upscope $end
$enddefinitions $end
$comment Show the parameter values. $end
$dumpall
$end
#0
$dumpvars
0%
0$
0#
0"
0!
$end
#20
1$
#40
0$
1#
#60
1!
1%
1$
#80
0%
0$
0#
1"
#100
1$
#120
0$
1#
#140
1%
1$
