Week2/Circuit3.v
module Circuit3 (
    A, 
    B, 
    C, 
    Z
);

    input A, B, C;
    output Z;
    wire w1, w2, w3;
    and G1 (w1, C, B);
    or G2 (w2, A, w1);
    and G3 (w3, B, A);
    or G4 (Z, w2, w3);
endmodule

Week2/Circuit3tb.v
module Circuit3tb;
    reg A, B, C;
    wire Z;
    Circuit3 M1 (A, B, C, Z);
    initial begin
        A = 1'b0;
        B = 1'b0;
        C = 1'b0;

        #20 A = 1'b0;
        B = 1'b0;
        C = 1'b1;

        #20 A = 1'b0;
        B = 1'b1;
        C = 1'b0;

        #20 A = 1'b0;
        B = 1'b1;
        C = 1'b1;

        #20 A = 1'b1;
        B = 1'b0;
        C = 1'b0;

        #20 A = 1'b1;
        B = 1'b0;
        C = 1'b1;

        #20 A = 1'b1;
        B = 1'b1;
        C = 1'b0;

        #20 A = 1'b1;
        B = 1'b1;
        C = 1'b1;
    end
    initial begin
        $monitor($time, "A = %b, B = %b, C = %b, Z = %b", A, B, C, Z);
    end
    initial begin
        $dumpfile("Circuit3.vcd");
        $dumpvars(0, Circuit3tb);
    end
endmodule

Week2/s3.vcd
$date
	Fri Aug 16 15:54:01 2024
$end
$version
	Icarus Verilog
$end
$timescale
	1s
$end
$scope module Circuit3tb $end
$var wire 1 ! Z $end
$var reg 1 " A $end
$var reg 1 # B $end
$var reg 1 $ C $end
$scope module M1 $end
$var wire 1 " A $end
$var wire 1 # B $end
$var wire 1 $ C $end
$var wire 1 ! Z $end
$var wire 1 % w1 $end
$var wire 1 & w2 $end
$var wire 1 ' w3 $end
$upscope $end
$upscope $end
$enddefinitions $end
$comment Show the parameter values. $end
$dumpall
$end
#0
$dumpvars
0'
0&
0%
0$
0#
0"
0!
$end
#20
1$
#40
0$
1#
#60
1!
1&
1%
1$
#80
0%
0$
0#
1"
#100
1$
#120
1'
0$
1#
#140
1%
1$
