Week4/mux_21.v
module mux_21(input wire I0,I1,J,output wire O);
assign O=J?I0:I1;
endmodule

Week4/mux4.v
module mux4(input wire [0:3]i,input wire j1,j0,output wire O);
wire t0,t1;
mux_21 mux2_0(i[0],i[1],j1,t0);
mux_21 mux2_1(i[2],i[3],j1,t1);
mux_21 mux2_3(t0,t1,j0,O);
endmodule

Week4/mux4tb.v
module mux4tb;
reg [0:3]ii;
reg s0,s1;
wire yy;
initial
begin
$dumpfile("mux4.vcd");
$dumpvars(0,mux4tb);
end
mux4 newMux(.i(ii),.j0(s0),.j1(s1),.O(yy));
initial
begin
ii=4'b0000;s0=1'b0;s1=1'b0;
#5 ii=4'b1000;s0=1'b0;s1=1'b0;
#5 ii=4'b0000;s0=1'b0;s1=1'b1;
#5 ii=4'b0100;s0=1'b0;s1=1'b1;
#5 ii=4'b0000;s0=1'b1;s1=1'b0;
#5 ii=4'b0010;s0=1'b1;s1=1'b0;
#5 ii=4'b0000;s0=1'b1;s1=1'b1;
#5 ii=4'b0001;s0=1'b1;s1=1'b1;
end
initial
begin
$monitor($time,"ii=%b,S1=%b,S0=%b,,y=%b",ii,s1,s0,yy);
end
endmodule

Week4/mux4.vcd
$date
	Sun Sep 01 12:45:56 2024
$end
$version
	Icarus Verilog
$end
$timescale
	1s
$end
$scope module mux4tb $end
$var wire 1 ! yy $end
$var reg 4 " ii [0:3] $end
$var reg 1 # s0 $end
$var reg 1 $ s1 $end
$scope module newMux $end
$var wire 4 % i [0:3] $end
$var wire 1 # j0 $end
$var wire 1 $ j1 $end
$var wire 1 & t1 $end
$var wire 1 ' t0 $end
$var wire 1 ! O $end
$scope module mux2_0 $end
$var wire 1 ( I0 $end
$var wire 1 ) I1 $end
$var wire 1 $ J $end
$var wire 1 ' O $end
$upscope $end
$scope module mux2_1 $end
$var wire 1 * I0 $end
$var wire 1 + I1 $end
$var wire 1 $ J $end
$var wire 1 & O $end
$upscope $end
$scope module mux2_3 $end
$var wire 1 ' I0 $end
$var wire 1 & I1 $end
$var wire 1 # J $end
$var wire 1 ! O $end
$upscope $end
$upscope $end
$upscope $end
$enddefinitions $end
$comment Show the parameter values. $end
$dumpall
$end
#0
$dumpvars
0+
0*
0)
0(
0'
0&
b0 %
0$
0#
b0 "
0!
$end
#5
1(
b1000 "
b1000 %
#10
0(
1$
b0 "
b0 %
#15
1)
b100 "
b100 %
#20
0)
0$
1#
b0 "
b0 %
#25
1*
b10 "
b10 %
#30
0*
1$
b0 "
b0 %
#35
1+
b1 "
b1 %
