Week3/fa.v
module fa (
    input wire a, b, cin,
    output wire sum, cout
);

    wire [4:0] t;

    xor x0 (t[0], a, b); 
    xor x1 (sum, t[0], cin); 

    and a0 (t[1], a, b); 
    and a1 (t[2], a, cin); 
    and a2 (t[3], b, cin); 

    or o0 (t[4], t[1], t[2]); 
    or o1 (cout, t[4], t[3]); 
endmodule

Week3/fatb.v
module fatb; 
    reg a, b, cin; 
    wire s, cout; 
    fa add1 ( a, b, cin, sum, cout ); 
    initial begin
        #0 a = 1'b0; b = 1'b0; cin = 1'b0; 
        #5 a = 1'b0; b = 1'b0; cin = 1'b1; 
        #5 a = 1'b0; b = 1'b0; cin = 1'b1;
        #5 a = 1'b0; b = 1'b1; cin = 1'b0; 
        #5 a = 1'b0; b = 1'b1; cin = 1'b1; 
        #5 a = 1'b1; b = 1'b0; cin = 1'b0; 
        #5 a = 1'b1; b = 1'b0; cin = 1'b1; 
        #5 a = 1'b1; b = 1'b1; cin = 1'b0; 
        #5 a = 1'b1; b = 1'b1; cin = 1'b1; 
    end
    initial begin 
        $monitor($time, "a=%b, b= %b, c= %b,sum= %b,carry= %b", a, b, cin, sum, cout); 
    end 
    initial begin 
        $dumpfile("fulladder.vcd"); 
        $dumpvars(0, fatb); 
    end 
endmodule

Week3/fulladder.vcd
$date
	Sun Aug 25 11:48:11 2024
$end
$version
	Icarus Verilog
$end
$timescale
	1s
$end
$scope module fatb $end
$var wire 1 ! sum $end
$var wire 1 " cout $end
$var reg 1 # a $end
$var reg 1 $ b $end
$var reg 1 % cin $end
$scope module add1 $end
$var wire 1 # a $end
$var wire 1 $ b $end
$var wire 1 % cin $end
$var wire 1 " cout $end
$var wire 1 ! sum $end
$var wire 5 & t [4:0] $end
$upscope $end
$upscope $end
$enddefinitions $end
$comment Show the parameter values. $end
$dumpall
$end
#0
$dumpvars
b0 &
0%
0$
0#
0"
0!
$end
#5
1!
1%
#15
1!
b1 &
0%
1$
#20
1"
0!
b1001 &
1%
#25
0"
1!
b1 &
0%
0$
1#
#30
1"
0!
b10101 &
1%
#35
0!
b10010 &
0%
1$
#40
1!
b11110 &
1%
